scan/__init__.py
scan/common.py
scan/config.ini
scan/config.py
scan/crawl.py
scan/log.py
scan/monitor.py
scan/response.py
scan/thread_pool.py
scan/util.py
scan/__pycache__/__init__.cpython-39.pyc
scan/__pycache__/common.cpython-39.pyc
scan/__pycache__/config.cpython-39.pyc
scan/__pycache__/crawl.cpython-39.pyc
scan/__pycache__/log.cpython-39.pyc
scan/__pycache__/monitor.cpython-39.pyc
scan/__pycache__/response.cpython-39.pyc
scan/__pycache__/thread_pool.cpython-39.pyc
scan/__pycache__/util.cpython-39.pyc
scan/core/__init__.py
scan/core/scheduler.py
scan/core/__pycache__/__init__.cpython-39.pyc
scan/core/__pycache__/scheduler.cpython-39.pyc
scan/core/spiders/__init__.py
scan/core/spiders/rabbit_spider.py
scan/core/spiders/simple_spider.py
scan/core/spiders/spider.py
scan/core/spiders/__pycache__/__init__.cpython-39.pyc
scan/core/spiders/__pycache__/rabbit_spider.cpython-39.pyc
scan/core/spiders/__pycache__/simple_spider.cpython-39.pyc
scan/core/spiders/__pycache__/spider.cpython-39.pyc
scan/database/__init__.py
scan/database/aior2.py
scan/database/db_redis.py
scan/database/kafka.py
scan/database/mongodb.py
scan/database/mysql.py
scan/database/oss.py
scan/database/pg.py
scan/database/rabbitmq.py
scan/database/wasabi.py
scan/database/__pycache__/__init__.cpython-39.pyc
scan/database/__pycache__/aior2.cpython-39.pyc
scan/database/__pycache__/db_redis.cpython-39.pyc
scan/database/__pycache__/kafka.cpython-39.pyc
scan/database/__pycache__/mongodb.cpython-39.pyc
scan/database/__pycache__/oss.cpython-39.pyc
scan/database/__pycache__/pg.cpython-39.pyc
scan/database/__pycache__/rabbitmq.cpython-39.pyc
scan/database/__pycache__/wasabi.cpython-39.pyc
scan/docs/proxy_switchyomega-2.5.20/AUTHORS
scan/docs/proxy_switchyomega-2.5.20/COPYING
scan/docs/proxy_switchyomega-2.5.20/background.html
scan/docs/proxy_switchyomega-2.5.20/manifest.json
scan/docs/proxy_switchyomega-2.5.20/options.html
scan/docs/proxy_switchyomega-2.5.20/popup.html
hscan-4.3.0.dist-info/METADATA
hscan-4.3.0.dist-info/WHEEL
hscan-4.3.0.dist-info/top_level.txt
hscan-4.3.0.dist-info/RECORD
