Metadata-Version: 2.1
Name: hscan
Version: 4.3.0
Summary: A python framework
Home-page: https://github.com/jyangHe/hscan
Author: jyanghe
Author-email: jyanghe1023@gmail.com
Classifier: Programming Language :: Python :: 3
Classifier: License :: OSI Approved :: MIT License
Classifier: Operating System :: OS Independent
Requires-Python: >=3.8.0
Requires-Dist: httpx[http2]==0.27.2
Requires-Dist: requests==2.32.3
Requires-Dist: aiofiles==24.1.0
Requires-Dist: aio-pika==9.5.4
Requires-Dist: beautifulsoup4==4.12.3
Requires-Dist: redis==5.2.1
Requires-Dist: motor==3.6.0
Requires-Dist: Brotli==1.1.0
Requires-Dist: pymongo==4.9.2
Requires-Dist: chardet==5.2.0
Requires-Dist: asyncpg==0.30.0
Requires-Dist: aioboto3==13.2.0
Requires-Dist: aiomysql==0.2.0
Requires-Dist: curl-cffi==0.7.4
Requires-Dist: aiohttp==3.11.10
Requires-Dist: loguru==0.7.3
Requires-Dist: oss2==2.15.0
Requires-Dist: aiokafka==0.12.0
Requires-Dist: DrissionPage==4.1.0.14
Requires-Dist: tenacity==9.0.0
Requires-Dist: html5lib==1.1
